swarmauri_doc2vec_vectorstore/Doc2VecEmbedding.py
swarmauri_doc2vec_vectorstore/Doc2VecVectorStore.py
swarmauri_doc2vec_vectorstore/__init__.py
swarmauri_doc2vec_vectorstore-0.6.0.dev147.dist-info/METADATA
swarmauri_doc2vec_vectorstore-0.6.0.dev147.dist-info/WHEEL
swarmauri_doc2vec_vectorstore-0.6.0.dev147.dist-info/entry_points.txt
swarmauri_doc2vec_vectorstore-0.6.0.dev147.dist-info/RECORD
